convo_lang_iyio/__init__.py
convo_lang_iyio/convo-test.py
convo_lang_iyio/convo.js
convo_lang_iyio/convoLib.py
convo_lang_iyio/lights.convo
convo_lang_iyio-0.0.1.dist-info/METADATA
convo_lang_iyio-0.0.1.dist-info/WHEEL
convo_lang_iyio-0.0.1.dist-info/licenses/LICENSE
convo_lang_iyio-0.0.1.dist-info/RECORD
