Metadata-Version: 2.1
Name: convo_lang_iyio
Version: 0.0.1
Summary: A conversational prompting and programming language
Author-email: Scott Vance <scott@iyio.io>
License-File: LICENSE
Classifier: License :: OSI Approved :: MIT License
Classifier: Operating System :: OS Independent
Classifier: Programming Language :: Python :: 3
Requires-Python: >=3.8
